ansys/api/meshing/prime/__init__.py
ansys/api/meshing/prime/_version.py
ansys/api/meshing/prime/py.typed
ansys/api/meshing/prime/v1/prime.proto
ansys/api/meshing/prime/v1/prime_pb2.py
ansys/api/meshing/prime/v1/prime_pb2.pyi
ansys/api/meshing/prime/v1/prime_pb2_grpc.py
ansys/api/meshing/prime/v1/prime_pb2_grpc.pyi
ansys_api_meshing_prime-0.1.5.dist-info/licenses/LICENSE
ansys_api_meshing_prime-0.1.5.dist-info/METADATA
ansys_api_meshing_prime-0.1.5.dist-info/WHEEL
ansys_api_meshing_prime-0.1.5.dist-info/entry_points.txt
ansys_api_meshing_prime-0.1.5.dist-info/top_level.txt
ansys_api_meshing_prime-0.1.5.dist-info/RECORD
