Metadata-Version: 2.4
Name: ansys-api-meshing-prime
Version: 0.1.5
Summary: Autogenerated python gRPC interface package for ansys-api-meshing-prime
Home-page: https://github.com/ansys/ansys-api-meshing-prime
Author: ANSYS, Inc.
Author-email: support@ansys.com
License: MIT
Requires-Python: >=3.8, <4
License-File: LICENSE
Requires-Dist: grpcio~=1.46
Requires-Dist: protobuf<5,>=3.19
Dynamic: author
Dynamic: author-email
Dynamic: description
Dynamic: description-content-type
Dynamic: home-page
Dynamic: license
Dynamic: license-file
Dynamic: requires-dist
Dynamic: requires-python
Dynamic: summary
